boleto/__init__.py
boleto-0.1.1.dist-info/METADATA
boleto-0.1.1.dist-info/WHEEL
boleto-0.1.1.dist-info/RECORD
