Metadata-Version: 2.1
Name: boleto
Version: 0.1.1
Summary: SDK para geração de boletos bancários
Home-page: https://github.com/pagme-dev/boleto-sdk-python
Author: GabrielCarvalho
Author-email: gabrielcarvalho.workk@gmail.com
Requires-Python: >=3.7,<3.12
Classifier: Programming Language :: Python :: 3
Classifier: Programming Language :: Python :: 3.7
Classifier: Programming Language :: Python :: 3.8
Classifier: Programming Language :: Python :: 3.9
Classifier: Programming Language :: Python :: 3.10
Classifier: Programming Language :: Python :: 3.11
Project-URL: Repository, https://github.com/pagme-dev/boleto-sdk-python
